pycountsik/__init__.py
pycountsik/data/__init__.py
pycountsik/data/flatland.txt
pycountsik/datasets.py
pycountsik/hello.py
pycountsik/plotting.py
pycountsik/pycounts.py
pycountsik-0.4.0.dist-info/METADATA
pycountsik-0.4.0.dist-info/WHEEL
pycountsik-0.4.0.dist-info/LICENSE
pycountsik-0.4.0.dist-info/RECORD
