Metadata-Version: 2.1
Name: pycountsik
Version: 0.4.0
Summary: 
Author: Aivoric
Requires-Python: >=3.10.0
Classifier: Programming Language :: Python :: 3
Classifier: Programming Language :: Python :: 3.10
Classifier: Programming Language :: Python :: 3.11
Requires-Dist: matplotlib (>=3.6.3)
